cross_service_auth/__init__.py
cross_service_auth/authentication.py
cross_service_auth-1.0.2.dist-info/METADATA
cross_service_auth-1.0.2.dist-info/WHEEL
cross_service_auth-1.0.2.dist-info/top_level.txt
cross_service_auth-1.0.2.dist-info/RECORD
